<?xml version="1.0" encoding="utf-8"?>
<Orders>
  <order>
    <OrderID>500101</OrderID>
    <CustomerName>yuyu</CustomerName>
    <CustomerEmail>uytuyt</CustomerEmail>
    <CustomerAddress>uytuyttuy</CustomerAddress>
    <OrderDate>2023-02-22T00:00:00</OrderDate>
    <ShipDate>2023-02-22T17:59:32.7856926+02:00</ShipDate>
    <DeliveryDate>2023-02-22T17:59:37.7846619+02:00</DeliveryDate>
  </order>
  <order>
    <OrderID>500102</OrderID>
    <CustomerName>rrr</CustomerName>
    <CustomerEmail>rrr</CustomerEmail>
    <CustomerAddress>rrrr</CustomerAddress>
    <OrderDate>2023-02-22T00:00:00</OrderDate>
    <ShipDate>2023-02-22T18:03:46.8960015+02:00</ShipDate>
    <DeliveryDate>2023-02-22T18:05:17.3763198+02:00</DeliveryDate>
  </order>
  <order>
    <OrderID>500103</OrderID>
    <CustomerName>yt</CustomerName>
    <CustomerEmail>rrryt</CustomerEmail>
    <CustomerAddress>reerer</CustomerAddress>
    <OrderDate>2023-02-22T00:00:00</OrderDate>
    <ShipDate>2023-02-22T18:03:48.2346514+02:00</ShipDate>
    <DeliveryDate>2023-02-22T18:05:19.7306488+02:00</DeliveryDate>
  </order>
  <order>
    <OrderID>500104</OrderID>
    <CustomerName>yt</CustomerName>
    <CustomerEmail>yt</CustomerEmail>
    <CustomerAddress>yt</CustomerAddress>
    <OrderDate>2023-02-22T00:00:00</OrderDate>
    <ShipDate>2023-02-22T18:10:55.3808719+02:00</ShipDate>
    <DeliveryDate>2023-02-22T18:10:59.9869543+02:00</DeliveryDate>
  </order>
  <order>
    <OrderID>500105</OrderID>
    <CustomerName>oi</CustomerName>
    <CustomerEmail>oi</CustomerEmail>
    <CustomerAddress>oi</CustomerAddress>
    <OrderDate>2023-02-22T00:00:00</OrderDate>
    <ShipDate>2023-02-22T18:10:58.4070193+02:00</ShipDate>
    <DeliveryDate>2023-02-22T18:11:02.9724992+02:00</DeliveryDate>
  </order>
  <order>
    <OrderID>500106</OrderID>
    <CustomerName>sd</CustomerName>
    <CustomerEmail>sd</CustomerEmail>
    <CustomerAddress>sd</CustomerAddress>
    <OrderDate>2023-02-22T00:00:00</OrderDate>
    <ShipDate>2023-02-22T18:14:14.5208992+02:00</ShipDate>
    <DeliveryDate>2023-02-22T18:14:17.8722972+02:00</DeliveryDate>
  </order>
  <order>
    <OrderID>500107</OrderID>
    <CustomerName>yu</CustomerName>
    <CustomerEmail>yu</CustomerEmail>
    <CustomerAddress>yu</CustomerAddress>
    <OrderDate>2023-02-22T00:00:00</OrderDate>
    <ShipDate>2023-02-22T18:16:14.9983274+02:00</ShipDate>
    <DeliveryDate>2023-02-22T18:16:37.6536582+02:00</DeliveryDate>
  </order>
  <order>
    <OrderID>500108</OrderID>
    <CustomerName>sd</CustomerName>
    <CustomerEmail>sd</CustomerEmail>
    <CustomerAddress>sd</CustomerAddress>
    <OrderDate>2023-02-22T00:00:00</OrderDate>
    <ShipDate>2023-02-22T18:18:31.5445921+02:00</ShipDate>
    <DeliveryDate>2023-02-22T18:27:39.3502415+02:00</DeliveryDate>
  </order>
  <order>
    <OrderID>500109</OrderID>
    <CustomerName>yu</CustomerName>
    <CustomerEmail>yuuyy</CustomerEmail>
    <CustomerAddress>yuyuyu</CustomerAddress>
    <OrderDate>2023-02-22T00:00:00</OrderDate>
    <ShipDate>2023-02-22T18:27:26.6576328+02:00</ShipDate>
    <DeliveryDate>2023-02-22T18:27:41.069732+02:00</DeliveryDate>
  </order>
  <order>
    <OrderID>500110</OrderID>
    <CustomerName>sf</CustomerName>
    <CustomerEmail>sf</CustomerEmail>
    <CustomerAddress>fds</CustomerAddress>
    <OrderDate>2023-02-22T00:00:00</OrderDate>
    <ShipDate>2023-02-22T18:27:31.1034909+02:00</ShipDate>
    <DeliveryDate>2023-02-22T18:42:37.9109887+02:00</DeliveryDate>
  </order>
  <order>
    <OrderID>500111</OrderID>
    <CustomerName>tyytr</CustomerName>
    <CustomerEmail>ytrytr</CustomerEmail>
    <CustomerAddress>ytrytr</CustomerAddress>
    <OrderDate>2023-02-22T00:00:00</OrderDate>
    <ShipDate>2023-02-22T18:27:34.1173397+02:00</ShipDate>
    <DeliveryDate>2023-02-22T19:02:21.8960342+02:00</DeliveryDate>
  </order>
  <order>
    <OrderID>500112</OrderID>
    <CustomerName>er</CustomerName>
    <CustomerEmail>rt</CustomerEmail>
    <CustomerAddress>rttrt</CustomerAddress>
    <OrderDate>2023-02-22T00:00:00</OrderDate>
    <ShipDate>2023-02-22T18:51:16.2205591+02:00</ShipDate>
    <DeliveryDate>2023-02-22T19:07:35.6625719+02:00</DeliveryDate>
  </order>
  <order>
    <OrderID>500123</OrderID>
    <CustomerName>zxd</CustomerName>
    <CustomerEmail>zcvx@f</CustomerEmail>
    <CustomerAddress>zc</CustomerAddress>
    <OrderDate>2023-02-23T00:00:00</OrderDate>
    <ShipDate>2023-02-23T14:27:30.4080963+02:00</ShipDate>
    <DeliveryDate>2023-02-23T15:13:09.3865459+02:00</DeliveryDate>
  </order>
  <order>
    <OrderID>500113</OrderID>
    <CustomerName>rtyu</CustomerName>
    <CustomerEmail>kjkjb</CustomerEmail>
    <CustomerAddress>mm</CustomerAddress>
    <OrderDate>2023-02-22T00:00:00</OrderDate>
    <ShipDate>2023-02-23T15:12:30.1296289+02:00</ShipDate>
    <DeliveryDate>2023-02-23T15:13:12.557996+02:00</DeliveryDate>
  </order>
  <order>
    <OrderID>500114</OrderID>
    <CustomerName>erty</CustomerName>
    <CustomerEmail>qwerty</CustomerEmail>
    <CustomerAddress>bb</CustomerAddress>
    <OrderDate>2023-02-22T00:00:00</OrderDate>
    <ShipDate>2023-02-23T15:12:33.3803752+02:00</ShipDate>
    <DeliveryDate>2023-02-23T15:13:14.6816916+02:00</DeliveryDate>
  </order>
  <order>
    <OrderID>500115</OrderID>
    <CustomerName>bn</CustomerName>
    <CustomerEmail>n</CustomerEmail>
    <CustomerAddress>nn</CustomerAddress>
    <OrderDate>2023-02-22T00:00:00</OrderDate>
    <ShipDate>2023-02-23T15:12:38.2371046+02:00</ShipDate>
    <DeliveryDate>2023-02-23T15:29:42.7132169+02:00</DeliveryDate>
  </order>
  <order>
    <OrderID>500116</OrderID>
    <CustomerName>mn</CustomerName>
    <CustomerEmail>nk</CustomerEmail>
    <CustomerAddress>nk</CustomerAddress>
    <OrderDate>2023-02-22T00:00:00</OrderDate>
    <ShipDate>2023-02-23T15:12:43.3347707+02:00</ShipDate>
    <DeliveryDate>2023-02-23T15:30:07.7312488+02:00</DeliveryDate>
  </order>
  <order>
    <OrderID>500117</OrderID>
    <CustomerName>d</CustomerName>
    <CustomerEmail>d@d.lk</CustomerEmail>
    <CustomerAddress>d</CustomerAddress>
    <OrderDate>2023-02-22T00:00:00</OrderDate>
    <ShipDate>2023-02-23T15:12:48.030879+02:00</ShipDate>
    <DeliveryDate>2023-02-23T16:08:29.321889+02:00</DeliveryDate>
  </order>
  <order>
    <OrderID>500122</OrderID>
    <CustomerName>zxd</CustomerName>
    <CustomerEmail>zcvx@f</CustomerEmail>
    <CustomerAddress>zc</CustomerAddress>
    <OrderDate>2023-02-23T00:00:00</OrderDate>
    <ShipDate>2023-02-23T15:58:10.9248554+02:00</ShipDate>
    <DeliveryDate>2023-02-23T16:08:34.4952597+02:00</DeliveryDate>
  </order>
  <order>
    <OrderID>500118</OrderID>
    <CustomerName>g</CustomerName>
    <CustomerEmail>g@g.k</CustomerEmail>
    <CustomerAddress>j</CustomerAddress>
    <OrderDate>2023-02-22T00:00:00</OrderDate>
    <ShipDate>2023-02-23T16:07:32.5813044+02:00</ShipDate>
    <DeliveryDate>2023-02-23T16:08:36.4710827+02:00</DeliveryDate>
  </order>
  <order>
    <OrderID>500119</OrderID>
    <CustomerName>hi</CustomerName>
    <CustomerEmail>ih@hi</CustomerEmail>
    <CustomerAddress>iknow</CustomerAddress>
    <OrderDate>2023-02-23T00:00:00</OrderDate>
    <ShipDate>2023-02-23T16:07:35.8923477+02:00</ShipDate>
    <DeliveryDate>2023-02-23T16:08:40.2550945+02:00</DeliveryDate>
  </order>
  <order>
    <OrderID>500120</OrderID>
    <CustomerName>q</CustomerName>
    <CustomerEmail>q@s</CustomerEmail>
    <CustomerAddress>w</CustomerAddress>
    <OrderDate>2023-02-23T00:00:00</OrderDate>
    <ShipDate>2023-02-23T16:42:40.7214714+02:00</ShipDate>
    <DeliveryDate>2023-02-23T16:42:47.7204946+02:00</DeliveryDate>
  </order>
  <order>
    <OrderID>500121</OrderID>
    <CustomerName>sdf</CustomerName>
    <CustomerEmail>s@d</CustomerEmail>
    <CustomerAddress>sdf</CustomerAddress>
    <OrderDate>2023-02-23T00:00:00</OrderDate>
    <ShipDate>2023-02-23T16:42:45.8043589+02:00</ShipDate>
    <DeliveryDate>2023-02-23T17:44:38.4255184+02:00</DeliveryDate>
  </order>
</Orders>